{
  "requestsFinished": 0,
  "requestsFailed": 0,
  "requestsRetries": 0,
  "requestsFailedPerMinute": 0,
  "requestsFinishedPerMinute": 0,
  "requestMinDurationMillis": null,
  "requestMaxDurationMillis": 0,
  "requestTotalFailedDurationMillis": 0,
  "requestTotalFinishedDurationMillis": 0,
  "crawlerStartedAt": "2026-04-20T02:04:51.699Z",
  "crawlerFinishedAt": "2026-04-20T02:04:51.744Z",
  "statsPersistedAt": "2026-04-20T02:04:51.744Z",
  "crawlerRuntimeMillis": 154,
  "crawlerLastStartTimestamp": 1776650691590,
  "requestRetryHistogram": [],
  "statsId": 79,
  "requestAvgFailedDurationMillis": null,
  "requestAvgFinishedDurationMillis": null,
  "requestTotalDurationMillis": 0,
  "requestsTotal": 0,
  "requestsWithStatusCode": {},
  "errors": {},
  "retryErrors": {}
}