{
  "requestsFinished": 0,
  "requestsFailed": 0,
  "requestsRetries": 0,
  "requestsFailedPerMinute": 0,
  "requestsFinishedPerMinute": 0,
  "requestMinDurationMillis": null,
  "requestMaxDurationMillis": 0,
  "requestTotalFailedDurationMillis": 0,
  "requestTotalFinishedDurationMillis": 0,
  "crawlerStartedAt": "2026-04-19T19:18:24.719Z",
  "crawlerFinishedAt": "2026-04-19T19:18:24.756Z",
  "statsPersistedAt": "2026-04-19T19:18:24.756Z",
  "crawlerRuntimeMillis": 169,
  "crawlerLastStartTimestamp": 1776626304587,
  "requestRetryHistogram": [],
  "statsId": 30,
  "requestAvgFailedDurationMillis": null,
  "requestAvgFinishedDurationMillis": null,
  "requestTotalDurationMillis": 0,
  "requestsTotal": 0,
  "requestsWithStatusCode": {},
  "errors": {},
  "retryErrors": {}
}